tfx/components/__init__.py
tfx/components/base/__init__.py
tfx/components/base/base_component.py
tfx/components/base/base_driver.py
tfx/components/base/base_executor.py
tfx/components/base/base_node.py
tfx/components/base/executor_spec.py
tfx/components/bulk_inferrer/__init__.py
tfx/components/bulk_inferrer/component.py
tfx/components/bulk_inferrer/component_test.py
tfx/components/bulk_inferrer/executor.py
tfx/components/bulk_inferrer/executor_test.py
tfx/components/bulk_inferrer/prediction_to_example_utils.py
tfx/components/bulk_inferrer/prediction_to_example_utils_test.py
tfx/components/common_nodes/__init__.py
tfx/components/distribution_validator/__init__.py
tfx/components/distribution_validator/component.py
tfx/components/distribution_validator/component_test.py
tfx/components/distribution_validator/executor.py
tfx/components/distribution_validator/executor_test.py
tfx/components/distribution_validator/utils.py
tfx/components/distribution_validator/utils_test.py
tfx/components/evaluator/__init__.py
tfx/components/evaluator/component.py
tfx/components/evaluator/component_test.py
tfx/components/evaluator/constants.py
tfx/components/evaluator/executor.py
tfx/components/evaluator/executor_test.py
tfx/components/example_diff/__init__.py
tfx/components/example_diff/component.py
tfx/components/example_diff/component_test.py
tfx/components/example_diff/executor.py
tfx/components/example_diff/executor_test.py
tfx/components/example_gen/__init__.py
tfx/components/example_gen/base_example_gen_executor.py
tfx/components/example_gen/base_example_gen_executor_test.py
tfx/components/example_gen/component.py
tfx/components/example_gen/component_test.py
tfx/components/example_gen/driver.py
tfx/components/example_gen/driver_test.py
tfx/components/example_gen/input_processor.py
tfx/components/example_gen/input_processor_test.py
tfx/components/example_gen/utils.py
tfx/components/example_gen/utils_test.py
tfx/components/example_gen/write_split.py
tfx-1.16.0.dist-info/LICENSE
tfx-1.16.0.dist-info/METADATA
tfx-1.16.0.dist-info/WHEEL
tfx-1.16.0.dist-info/entry_points.txt
tfx-1.16.0.dist-info/namespace_packages.txt
tfx-1.16.0.dist-info/top_level.txt
tfx-1.16.0.dist-info/RECORD
