Metadata-Version: 2.1
Name: tfx
Version: 1.16.0
Summary: TensorFlow Extended (TFX) is a TensorFlow-based general-purpose machine learning platform implemented at Google.
Home-page: https://www.tensorflow.org/tfx
Download-URL: https://github.com/tensorflow/tfx/tags
Author-email: Google LLC <tensorflow-extended-dev@googlegroups.com>
License: 
Project-URL: Homepage, https://www.tensorflow.org/tfx
Project-URL: Repository, https://github.com/tensorflow/tfx
Keywords: tensorflow,tfx
Classifier: Development Status :: 5 - Production/Stable
Classifier: Intended Audience :: Developers
Classifier: Intended Audience :: Education
Classifier: Intended Audience :: Science/Research
Classifier: License :: OSI Approved :: Apache Software License
Classifier: Operating System :: OS Independent
Classifier: Programming Language :: Python
Classifier: Programming Language :: Python :: 3
Classifier: Programming Language :: Python :: 3.9
Classifier: Programming Language :: Python :: 3.10
Classifier: Programming Language :: Python :: 3 :: Only
Classifier: Topic :: Scientific/Engineering
Classifier: Topic :: Scientific/Engineering :: Artificial Intelligence
Classifier: Topic :: Scientific/Engineering :: Mathematics
Classifier: Topic :: Software Development
Classifier: Topic :: Software Development :: Libraries
Classifier: Topic :: Software Development :: Libraries :: Python Modules
Requires-Python: <3.11,>=3.9
License-File: LICENSE
Requires-Dist: ml-pipelines-sdk==1.16.0
Requires-Dist: absl-py<2.0.0,>=0.9
Requires-Dist: ml-metadata<1.17.0,>=1.16.0
Requires-Dist: packaging>=22
Requires-Dist: portpicker<2,>=1.3.1
Requires-Dist: protobuf<5,>=3.20.3
Requires-Dist: docker<8,>=7
Requires-Dist: google-apitools<1,>=0.5
Requires-Dist: google-api-python-client<2,>=1.8
Requires-Dist: jinja2<4,>=2.7.3
Requires-Dist: typing-extensions<5
Requires-Dist: apache-beam[gcp]<3,>=2.47
Requires-Dist: attrs<24,>=19.3.0
Requires-Dist: click<9,>=7
Requires-Dist: google-api-core<3
Requires-Dist: google-cloud-aiplatform<2,>=1.6.2
Requires-Dist: google-cloud-bigquery<4,>=3
Requires-Dist: grpcio<2,>=1.28.1
Requires-Dist: keras-tuner!=1.4.0,!=1.4.1,<2,>=1.0.4
Requires-Dist: kubernetes<27,>=10.0.1
Requires-Dist: numpy<2,>=1.16
Requires-Dist: pyarrow<11,>=10
Requires-Dist: orjson!=3.10.7
Requires-Dist: scipy<1.13
Requires-Dist: scikit-learn==1.5.1
Requires-Dist: pyyaml<7,>=6
Requires-Dist: tensorflow<2.17,>=2.16.0
Requires-Dist: tensorflow-hub<0.16,>=0.15.0
Requires-Dist: tensorflow-data-validation<1.17.0,>=1.16.1
Requires-Dist: tensorflow-model-analysis<0.48.0,>=0.47.0
Requires-Dist: tensorflow-serving-api<2.17,>=2.16
Requires-Dist: tensorflow-transform<1.17.0,>=1.16.0
Requires-Dist: tfx-bsl<1.17.0,>=1.16.1
Provides-Extra: docker-image
Requires-Dist: kfp>=2; extra == "docker-image"
Requires-Dist: kfp-pipeline-spec>=0.2.2; extra == "docker-image"
Requires-Dist: mmh<3,>=2.2; extra == "docker-image"
Requires-Dist: python-snappy>=0.7; extra == "docker-image"
Requires-Dist: tensorflow-cloud<0.2,>=0.1; extra == "docker-image"
Requires-Dist: tensorflow-io<=0.24.0,>=0.9.0; extra == "docker-image"
Provides-Extra: airflow
Requires-Dist: apache-airflow[mysql]<3,>=1.10.14; extra == "airflow"
Provides-Extra: flax
Requires-Dist: jax<0.4.24; extra == "flax"
Requires-Dist: jaxlib<0.4.24; extra == "flax"
Requires-Dist: flax<1; extra == "flax"
Requires-Dist: optax<1; extra == "flax"
Provides-Extra: kfp
Requires-Dist: kfp>=2; extra == "kfp"
Requires-Dist: kfp-pipeline-spec>=0.2.2; extra == "kfp"
Provides-Extra: tfjs
Requires-Dist: tensorflowjs<5,>=4.5; extra == "tfjs"
Provides-Extra: tf-ranking
Requires-Dist: tensorflow-ranking<0.6,>=0.5; extra == "tf-ranking"
Requires-Dist: struct2tensor<0.48.0,>=0.47.0; extra == "tf-ranking"
Provides-Extra: tfdf
Requires-Dist: tensorflow-decision-forests<2,>=1.8.1; extra == "tfdf"
Provides-Extra: tflite-support
Requires-Dist: flatbuffers>=1.12; extra == "tflite-support"
Requires-Dist: tflite-support<0.4.5,>=0.4.3; extra == "tflite-support"
Provides-Extra: examples
Requires-Dist: presto-python-client<0.8,>=0.7; extra == "examples"
Requires-Dist: slackclient<3,>=2.8.2; extra == "examples"
Requires-Dist: websocket-client<1,>=0.57; extra == "examples"
Requires-Dist: tensorflow-text<3,>=1.15.1; extra == "examples"
Requires-Dist: scikit-learn<2,>=1.0; extra == "examples"
Requires-Dist: tensorflow-cloud<0.2,>=0.1; extra == "examples"
Provides-Extra: test
Requires-Dist: apache-airflow[mysql]<3,>=1.10.14; extra == "test"
Requires-Dist: kfp>=2; extra == "test"
Requires-Dist: kfp-pipeline-spec>=0.2.2; extra == "test"
Requires-Dist: pytest<=8,>=5; extra == "test"
Requires-Dist: pytest-subtests==0.13.1; extra == "test"
Provides-Extra: docs
Requires-Dist: mkdocs; extra == "docs"
Requires-Dist: mkdocstrings[python]; extra == "docs"
Requires-Dist: mkdocs-material; extra == "docs"
Requires-Dist: griffe-inherited-docstrings; extra == "docs"
Requires-Dist: mkdocs-autorefs; extra == "docs"
Requires-Dist: mkdocs-jupyter; extra == "docs"
Requires-Dist: mkdocs-caption; extra == "docs"
Requires-Dist: markdown-grid-tables; extra == "docs"
Provides-Extra: all
Requires-Dist: apache-airflow[mysql]<3,>=1.10.14; extra == "all"
Requires-Dist: kfp>=2; extra == "all"
Requires-Dist: kfp-pipeline-spec>=0.2.2; extra == "all"
Requires-Dist: pytest<=8,>=5; extra == "all"
Requires-Dist: pytest-subtests==0.13.1; extra == "all"
Requires-Dist: tensorflowjs<5,>=4.5; extra == "all"
Requires-Dist: flatbuffers>=1.12; extra == "all"
Requires-Dist: tflite-support<0.4.5,>=0.4.3; extra == "all"
Requires-Dist: tensorflow-ranking<0.6,>=0.5; extra == "all"
Requires-Dist: struct2tensor<0.48.0,>=0.47.0; extra == "all"
Requires-Dist: tensorflow-decision-forests<2,>=1.8.1; extra == "all"
Requires-Dist: jax<0.4.24; extra == "all"
Requires-Dist: jaxlib<0.4.24; extra == "all"
Requires-Dist: flax<1; extra == "all"
Requires-Dist: optax<1; extra == "all"
Requires-Dist: presto-python-client<0.8,>=0.7; extra == "all"
Requires-Dist: slackclient<3,>=2.8.2; extra == "all"
Requires-Dist: websocket-client<1,>=0.57; extra == "all"
Requires-Dist: tensorflow-text<3,>=1.15.1; extra == "all"
Requires-Dist: scikit-learn<2,>=1.0; extra == "all"
Requires-Dist: tensorflow-cloud<0.2,>=0.1; extra == "all"
